[
  {
    "id": "001",
    "name": "MintBlue",
    "desc": "一个有趣的人",
    "linkUrl": "https://www.mintblue.top",
    "imageUrl": "https://conf.mintblue.top/links/mintblue.jpeg"
  },
  {
    "id": "002",
    "name": "zzhack",
    "desc": "一个有趣的人",
    "linkUrl": "https://www.zzhack.fun/",
    "imageUrl": "https://conf.mintblue.top/links/mintblue.jpeg"
  },
  {
    "id": "003",
    "name": "Fatpandac",
    "desc": "不知道写啥的个人博客",
    "linkUrl": "https://www.fatpandac.com/",
    "imageUrl": "https://avatars.githubusercontent.com/u/30423976?v=4"
  }
]